Metadata-Version: 1.0
Name: dsnd-probability-0108-v1
Version: 1.0
Summary: Gaussian and Binomial distributions
Home-page: UNKNOWN
Author: Utkarsh Bansal
Author-email: UNKNOWN
License: UNKNOWN
Platform: UNKNOWN
